{
  "title": "Lockdown Warriors Cup/Phase 1",
  "page_id": 77129,
  "revision_id": 709832,
  "revision_parent_id": 706645,
  "revision_timestamp": "2026-06-18T11:53:07Z",
  "years": [
    2021
  ],
  "source_url": "https://liquipedia.net/pubgmobile/Lockdown_Warriors_Cup/Phase_1",
  "retrieved_at": "2026-07-17T09:32:10.810Z",
  "wikitext": "{{DISPLAYTITLE:Lockdown Warriors Cup: Phase 1}}\n{{Tabs static\n|name1=Phase 1|link1=Lockdown_Warriors_Cup/Phase 1\n|name2=Phase 2|link2=Lockdown_Warriors_Cup/Phase 2\n|this=1\n}}\n{{Infobox league\n|game=bgmi\n|liquipediatier=5\n|name=Lockdown Warriors Cup:Phase 1\n|icon=Lockdown Warriors Cup logo icon.png\n|tickername=Lockdown Warriors Cup: Phase 1\n|shortname=LWC:P1\n|image=Lockdown Warriors Cup logo icon.png\n|type=Online\n|team_number=18\n|series=Lockdown Warriors Cup\n|organizer=GOG ESPORTS\n|organizer-link=https://www.instagram.com/gogesportsindia/\n|sponsor=[https://www.instagram.com/gogesportsindia/ GOG ESPORTS]\n|mode=squads\n|prizepoolusd=\n|perspective=tpp\n|localcurrency=inr\n|prizepool=25,000\n|country=India\n|sdate=2021-08-30\n|edate=2021-09-01\n|instagram=gogesportsindia\n|web=\n|discord=ARvAPDuEFD\n|facebook=/gangsofgamingpurr?tsid=0.9335058100592506&source=result&refsrc=deprecated&_rdr\n|youtube=channel/UCRYiokeeou0YgtV-4f0pe0Q\n}}\n'''''[https://www.instagram.com/gogesportsindia/ GOG ESPORTS]''''' present a BGMI tournament called the ''' Lockdown Warriors Cup  ''' with a prize pool of ₹1,00,000. Phase 1 of the tournament features underdog teams competing for a prize pool of ₹25,000\n\n==About==\n===Broadcast Talent===\n{{broadcasterCard\n|position= Hindi Commentator |lang=en\n|b1=Jeet Gaming|b1flag=in|b1name=Jeet Sardar\n}}\n\n===Format===\n''''' Lockdown Warriors Cup Phase 1:''' 14th August 2021 to 1st September 2021.''\n\n* '''''Round 1:''' 14th August 2021 to 18th August 2021''\n** '' A total of 4000 teams will play in Round 1\n** '' Teams to be divided into 200 groups''.\n** '' Each team will get to play a single match''\n** '' Top 2 Teams from each group will qualify for the Round 2''.\n** {{bgcolortext|up|''Top 400 teams}} advance to Round 2.''\n* '''''Round 2:''' 22nd August 2021 to 23rd August 2021''\n** '' A total of 400 teams will play in Round 2\n** '' Teams to be divided into 20 groups''.\n** '' Each team will get to play a single match''\n** '' Top 2 Teams from each group will qualify for the Semi Finals''.\n** {{bgcolortext|up|''Top 40 teams}} advance to Semi Finals.''\n* '''''Semi Finals:''' 24th August 2021 to 25th August 2021''\n** '' A total of 40 teams will play in the Semi Finals''\n** '' Teams to be divided into 3 groups''.\n** '' Each team will get to play a total of 6 matches''\n** '' Top 6 Teams from each group will qualify for the Grand Finals''.\n** {{bgcolortext|up|''Top 18 teams}} will advance to Grand Finals.''\n* '''''Grand Finals:''' 30th August 2021 to 1st September 2021''\n** '' A total of 18 qualified teams will play in the Grand Finals''\n** '' Teams will get to play a total of 12 matches in a period of 3 days''\n** '' Each day will feature a total of 4 matches''\n====Matchdays====\n* ''3 Matchdays:  4 Matches Each Day.''\n** '''''Map Rotation''''': ''E>>M>>S>>E''\n\n====Allocations====\n{{bgcolortext|up|''Top 3}} teams from the overall standings will qualify for [[Lockdown_Warriors_Cup/Phase 2|Phase 2]]\n\n====Points Distribution====\n{{MatchScoringPointsTable|killterm=kill\n|{{Json|place=1|points=15|place2=6    |points2=4}}\n|{{Json|place=2|points=12|place2=7    |points2=2}}\n|{{Json|place=3|points=10|place2=8-12 |points2=1}}\n|{{Json|place=4|points=8 |place2=13-18|points2=0}}\n|{{Json|place=5|points=6 }}\n}}\n\n===Prize Pool===\n₹ 25,000 {{Abbr/INR}} (≃ $342 {{Abbr/USD}} ) are spread among the teams as seen below:\n{{prize pool start team |cutafter=4|points=seed|localcurrency=inr}}\n{{prize pool slot team |place=1 |points=[[Lockdown Warriors_Cup/Phase 2|Phase 2]] |localprize=12,000|usdprize=|desire to rise}}\n{{prize pool slot team |place=2 |points=[[Lockdown Warriors_Cup/Phase 2|Phase 2]] |localprize=5,000|usdprize=|f4k x evn esports}}\n{{prize pool slot team |place=3 |points=[[Lockdown Warriors_Cup/Phase 2|Phase 2]] |localprize=3,000|usdprize=|now esports}}\n{{prize pool slot team |place=4 |points=0 |localprize=0|usdprize=0|subzero}}\n{{prize pool slot team |place=5 |points=0 |localprize=0|usdprize=0|team redxross}}\n{{prize pool slot team |place=6 |points=0 |localprize=0|usdprize=0|nova ind}}\n{{prize pool slot team |place=7 |points=0 |localprize=0|usdprize=0|oh reborn}}\n{{prize pool slot team |place=8 |points=0 |localprize=0|usdprize=0|vidivici esports}}\n{{prize pool slot team |place=9 |points=0 |localprize=0|usdprize=0|team egm}}\n{{prize pool slot team |place=10 |points=0 |localprize=0|usdprize=0|ssxjowai}}\n{{prize pool slot team |place=11 |points=0 |localprize=0|usdprize=0|vibez esports}}\n{{prize pool slot team |place=12 |points=0|localprize=0|usdprize=0|4 mation}}\n{{prize pool slot team |place=13 |points=0|localprize=0|usdprize=0|nf esports in}}\n{{prize pool slot team |place=14 |points=0|localprize=0|usdprize=0|belligerence}}\n{{prize pool slot team |place=15 |points=0 |localprize=0|usdprize=0|megadevils}}\n{{prize pool slot team |place=16 |points=0 |localprize=0|usdprize=0|legionxftw}}\n{{prize pool slot team |place=17 |points=0 |localprize=0|usdprize=0|cm esports}}\n{{prize pool slot team |place=dq |points=0 |localprize=0|usdprize=0|gld ils}}\n{{Prize pool end}}\n\n==Participants==\n{{TeamCardToggleButton}}\n{{TeamCard columns start|cols=4}}\n{{TeamCard\n|team=OH Reborn\n|p1=Amrit|p1flag=in\n|p2=Aayush|p2flag=in\n|p3=REAPER|p3flag=in\n|p4=NiCK|p4flag=in\n|p5=CENTAUR|p5flag=in\n|p6=|p6flag=in\n\n|qualifier=Finals Qualified\n}}\n{{TeamCard\n|team=SSxJOWAI\n|p1=OkiO|p1flag=in\n|p2=ZeReF|p2flag=in\n|p3=Barbie|p3flag=in\n|p4=RuSs|p4flag=in\n|p5=DARIA|p5flag=in\n|p6=|p6flag=in\n\n|qualifier=Finals Qualified\n}}\n{{TeamCard\n|team=4 MATION\n|p1=Aaryan|p1flag=in\n|p2=ShaDoW|p2flag=in\n|p3=BL4DEOP|p3flag=in\n|p4=DemiGod|p4flag=in\n|p5=NotSoPro|p5flag=in\n|p6=Electro|p6flag=in|p6link=Electro (Indian player)\n\n|qualifier=Finals Qualified\n}}\n{{TeamCard\n|team=SUBZERO\n|image=Subzero lightmode.png\n|p1=FAHAD|p1flag=in\n|p2=IZZO|p2flag=in\n|p3=KADLA|p3flag=in\n|p4=VENOM|p4flag=in |p4link=VENOM (Indian Player)\n|p5=GODKiL|p5flag=in\n|p6=|p6flag=in\n\n|qualifier=Finals Qualified\n}}\n{{TeamCard\n|team=Vidivici eSports\n|p1=SAHIL|p1flag=in\n|p2=ThunderYT|p2flag=in\n|p3=PRICEOP|p3flag=in\n|p4=JoKerOP|p4flag=in\n|p5=CHAPPALop|p5flag=in\n|p6=Nastik|p6flag=in\n\n|qualifier=Finals Qualified\n}}\n{{TeamCard\n|team=Team RedXross\n|p1=Arto|p1flag=in\n|p2=ArmXn|p2flag=in\n|p3=Zereƒ|p3flag=in\n|p4=NiKHilOP|p4flag=in\n|p5=Vamppyyyy|p5flag=in\n\n|qualifier=Finals Qualified \n}}\n{{TeamCard\n|team=CM Esports\n|p1=AMU|p1flag=in\n|p2=ASU|p2flag=in\n|p3=CRUNCHY|p3flag=in\n|p4=PalhaniaYT|p4flag=in\n|p5=REAPER|p5flag=in |p5link=REAPER (Indian Player)\n|p6=TabhiOP|p6flag=in\n\n|qualifier=Finals Qualified\n}}\n{{TeamCard\n|team=VibeZ eSports\n|p1=InTheEndit|p1flag=in\n|p2=AdityaJOD|p2flag=in\n|p3=WreckBTC|p3flag=in\n|p4=Itachi|p4flag=in |p4link=Itachi (Indian Player)\n|p5=WipeEmUp|p5flag=in\n|p6=|p6flag=in\n\n|qualifier=Finals Qualified\n}}\n{{TeamCard\n|team=F4K x EVN Esports\n|p1=WildCaT|p1flag=in\n|p2=In10se|p2flag=in\n|p3=Strange|p3flag=in\n|p4=Raker|p4flag=in\n|p5=VINI|p5flag=in\n|p6=GuruOP|p6flag=in\n|p7=KingsMan|p7flag=in\n|players=5\n|qualifier=Finals Qualified\n}}\n{{TeamCard\n|team=Belligerence\n|p1=KratosOP|p1flag=in\n|p2=SEXxY|p2flag=in\n|p3=TushiiOP|p3flag=in\n|p4=KARMA|p4flag=in\n|p5=LiGhTnInG|p5flag=in\n|p6=perfect|p6flag=in\n\n|qualifier=Finals Qualified\n}}\n{{TeamCard\n|team=MEGADEVILS\n|p1=JODBoi|p1flag=in\n|p2=RaVAN|p2flag=in\n|p3=RushGOD|p3flag=in\n|p4=ZURICH|p4flag=in\n|p5=AimGOD|p5flag=in\n|p6=COMMaNDO|p6flag=in\n\n|qualifier=Finals Qualified\n}}\n{{TeamCard\n|team=NF Esports\n|link=NF Esports (Indian Team)\n|image=\n|p1=DRUNKARDALPHA|p1flag=in\n|p2=RAVAN|p2flag=in\n|p3=KARMA|p3flag=in\n|p4=D3MON|p4flag=in\n|p5=REPTUS|p5flag=in\n|p6=|p6flag=in\n\n|qualifier=Finals Qualified\n}}\n{{TeamCard\n|team=Nova IND\n|p1=FAITH|p1flag=in\n|p2=NOTTTY|p2flag=in\n|p3=SAPPY|p3flag=in\n|p4=PIYUSH|p4flag=in\n|p5=EvoxYT|p5flag=in\n|p6=|p6flag=in\n\n|qualifier=Finals Qualified\n}}\n{{TeamCard\n|team=DESIRE TO RISE\n|p1=Hawkeye|p1flag=in\n|p2=F4LSH|p2flag=in\n|p3=Ronaq|p3flag=in\n|p4=VenoM|p4flag=in\n|p5=CHAMP|p5flag=in\n|p6=|p6flag=in\n\n|qualifier=Finals Qualified\n}}\n{{TeamCard\n|team=Team EGM\n|p1=AToMIC|p1flag=in\n|p2=69|p2flag=in\n|p3=SUPBOI|p3flag=in\n|p4=BlanK|p4flag=in\n|p5=GoJo|p5flag=in\n|p6=LulliPoP|p6flag=in\n\n|qualifier=Finals Qualified\n}}\n{{TeamCard\n|team=NOW Esports\n|p1=Tally|p1flag=in\n|p2=HunterR|p2flag=in\n|p3=Monk|p3flag=in |p3link=Monk (Indian Player)\n|p4=Jay|p4flag=in\n|p5=|p5flag=in\n|p6=|p6flag=in\n\n|qualifier=Finals Qualified\n}}\n{{TeamCard\n|team=LEGIONxFTW\n|p1=NFRO|p1flag=in\n|p2=DevL|p2flag=in\n|p3=ScoobyLust|p3flag=in\n|p4=CAP|p4flag=in\n|p5=LiQ|p5flag=in\n|p6=|p6flag=in\n\n|qualifier=Finals Qualified\n}}\n{{TeamCard\n|team=GLD ILS\n|notes=1\n|p1=|p1flag=in\n|p2=|p2flag=in\n|p3=|p3flag=in\n|p4=|p4flag=in\n|p5=|p5flag=in\n|p6=|p6flag=in\n\n|qualifier=Finals Qualified\n}}\n{{TeamCard columns end}}\n{{NoteBig\n|n1= '''''[[GLD ILS]] disqualified from the tournament for the suspected use of cheats and failing to provide POV'''''<ref name=\"gld ils dq\"> {{cite web|url=https://www.instagram.com/p/CTRGTDWHMpk/|title=TEAM IS PERMANENTLY BANNED FROM ALL GOG AND PARTNER EVENTS|date=2021-09-01|publisher='''GOG ESPORTS'''}}</ref> .\n}}\n\n==Results==\n{{OverallStandingsTable|title=Overall Standings|finished=true|showmatches=true\n|{{TeamOpponent|desire to rise|mp=12|pp=87|kp=57|total=144}}\n|{{TeamOpponent|team redxross|mp=12|pp=68|kp=69|total=137}}\n|{{TeamOpponent|f4k x evn esports|mp=12|pp=75|kp=61|total=136}}\n|{{TeamOpponent|nova ind|mp=12|pp=60|kp=74|total=134}}\n|{{TeamOpponent|subzero|mp=12|pp=62|kp=66|total=128}}\n|{{TeamOpponent|now esports|mp=12|pp=63|kp=62|total=125}}\n|{{TeamOpponent|oh reborn|mp=12|pp=54|kp=45|total=99}}\n|{{TeamOpponent|ssxjowai|mp=12|pp=55|kp=31|total=86}}\n|{{TeamOpponent|vidivici esports|mp=12|pp=49|kp=31|total=80}}\n|{{TeamOpponent|team egm|mp=12|pp=48|kp=30|total=78}}\n|{{TeamOpponent|belligerence|mp=12|pp=26|kp=26|total=52|tiebreaker=1}}\n|{{TeamOpponent|vibez esports|mp=12|pp=25|kp=27|total=52}}\n|{{TeamOpponent|4 mation|mp=12|pp=15|kp=29|total=44}}\n|{{TeamOpponent|nf esports in|mp=12|pp=11|kp=29|total=40}}\n|{{TeamOpponent|megadevils|mp=12|pp=17|kp=18|total=35}}\n|{{TeamOpponent|legionxftw|mp=12|pp=14|kp=10|total=24}}\n|{{TeamOpponent|cm esports|mp=12|pp=08|kp=11|total=19}}\n}}\n\n==Additional Content==\n===Streams===\n{{Streams\n|lang1=in |youtube1=Gangs Of Gamingpur\n}}\n\n====Finals VODs====\n{| class=\"sortable wikitable\" style=\"text-align:center;\"\n|-\n|-\n!width=\"100\"|VOD\n|width=\"60\"|'''Day-1'''\n|width=\"60\"|'''Day-2'''\n|width=\"60\"|'''Day-3'''\n|-\n!|Stream\n|{{YoutubeIcon|link=watch?v=QmX3Ny3euwI&}}\n|{{YoutubeIcon|link=watch?v=58TfW24Hsfw}}\n|{{YoutubeIcon|link=watch?v=I9-IzA-IVmE}}\n|-\n|}"
}
